codeet/__init__.py
codeet/Photo/photo.py
codeet-0.1.dist-info/METADATA
codeet-0.1.dist-info/WHEEL
codeet-0.1.dist-info/top_level.txt
codeet-0.1.dist-info/RECORD
