Metadata-Version: 2.4
Name: codeet
Version: 0.1
Summary: A helper package for 'codeet.ir'
Author-email: Codeet <help@codeet.ir>
License: MIT
Project-URL: Homepage, https://codeet.ir
Classifier: Programming Language :: Python :: 3
Classifier: License :: OSI Approved :: MIT License
Classifier: Operating System :: OS Independent
Requires-Python: >=3.10
